{
  "ACESSORIOS": "ACESSÓRIOS",
  "BERMUDA": "SHORTS E BERMUDA",
  "BLAZER": "BLAZER",
  "BLUSA": "BLUSA",
  "BLUSAS": "BLUSA",
  "BOARDSHORT": "SHORTS E BERMUDA",
  "BODY": "BODY",
  "BONE": "BONÉ",
  "CALCA": "CALÇA",
  "CALCADOS": "CALÇADOS",
  "CAMISA": "CAMISA",
  "CAMISETA": "CAMISETA",
  "CARDIGAN": "TRICÔT,SUÉTER E CARDIGAN",
  "CARTEIRA": "CARTEIRA",
  "CASACO": "CASACOS E JAQUETAS",
  "CASACOS": "CASACOS E JAQUETAS",
  "CHINELO": "CHINELO",
  "CINTO": "CINTO",
  "COLETE": "COLETE",
  "CONJUNTO": "CONJUNTO",
  "COSMETICOS": "COSMÉTICOS",
  "CROPPED": "CROPPED",
  "CUECA": "CUECA",
  "HIDRATANTE": "HIDRATANTE",
  "JAQUETA": "CASACOS E JAQUETAS",
  "JARDINEIRA": "JARDINEIRAS",
  "MACACAO": "MACACÕES",
  "MAIÔ": "MAIÔ",
  "MEIA": "MEIA",
  "MOCHILA": "MOCHILA",
  "OCULOS": "ÓCULOS",
  "PERFUME": "PERFUME",
  "POLO": "POLO",
  "REGATA": "REGATA",
  "SAIA": "SAIA",
  "SAPATENIS": "SAPATÊNIS",
  "SHORT VOLEY": "SHORTS E BERMUDAS",
  "SHORTS": "SHORTS E BERMUDA",
  "TOP": "TOP",
  "VESTIDO": "VESTIDO"
}
